akumasubtitler/__init__.py
akumasubtitler/subtitler.py
akumasubtitler/whisper_wrapper.py
akumasubtitler-0.1.6.dist-info/licenses/LICENSE
akumasubtitler-0.1.6.dist-info/METADATA
akumasubtitler-0.1.6.dist-info/WHEEL
akumasubtitler-0.1.6.dist-info/top_level.txt
akumasubtitler-0.1.6.dist-info/RECORD
