Metadata-Version: 2.4
Name: akumasubtitler
Version: 0.1.6
Summary: A tool for automatic subtitling
Author-email: akumanomi1988 <akumanomi1988@example.com>
License: MIT License
Project-URL: Homepage, https://github.com/akumanomi1988/AkumaSubtitler
Project-URL: Repository, https://github.com/akumanomi1988/AkumaSubtitler
Keywords: subtitles,whisper,video,moviepy
Classifier: Programming Language :: Python :: 3
Classifier: Programming Language :: Python :: 3.10
Classifier: Programming Language :: Python :: 3.11
Classifier: Programming Language :: Python :: 3.12
Classifier: License :: OSI Approved :: MIT License
Classifier: Operating System :: OS Independent
Requires-Python: >=3.10
License-File: LICENSE
Requires-Dist: moviepy==1.0.3
Requires-Dist: ffmpeg-python==0.2.0
Requires-Dist: tqdm==4.67.1
Provides-Extra: whisper
Requires-Dist: openai-whisper==20250625; extra == "whisper"
Requires-Dist: torch==2.8.0; extra == "whisper"
Dynamic: license-file
